LICENSE.txt
MANIFEST.in
README.rst
setup.cfg
setup.py
transfixed/__init__.py
transfixed/cqg_config.ini
transfixed/cqgfixtrader.py
transfixed/gain_config.ini
transfixed/gainfixtrader.py
transfixed/testfixtrader.py
transfixed/unit_tests.py
transfixed.egg-info/PKG-INFO
transfixed.egg-info/SOURCES.txt
transfixed.egg-info/dependency_links.txt
transfixed.egg-info/requires.txt
transfixed.egg-info/top_level.txt
transfixed/fix/FIX42.xml
transfixed/fix/FIX44.xml