Metadata-Version: 1.1
Name: transfixed
Version: 1.0.5
Summary: FIX TRADING LIBRARY
Home-page: https://github.com/th3sys/transfixed
Author: Alexy Shelest
Author-email: alexy@th3sys.com
License: MIT
Keywords: gain capital futures cqg quickfix fix protocol trading
Platform: any
Classifier: Programming Language :: Python :: 2.7
Classifier: Programming Language :: Python :: 3.6
